{
    "6493": {
        "M Navami Sampoorna Annadana Seva": {
            "Number": 1953524069,
            "additionalCost": 0,
            "count": 1,
            "sevaCost": 10000,
            "sevaId": 23,
            "sevaName": "M Navami Sampoorna Annadana Seva",
            "sevaTime": "08:00 AM",
            "sevaType": 3,
            "teerthaPrasada": 50
        },
        "Nithya Archane": {
            "Number": 0,
            "additionalCost": 0,
            "count": 1,
            "sevaCost": 0,
            "sevaId": 102,
            "sevaName": "Nithya Archane",
            "sevaTime": "08:00 AM",
            "sevaType": 0,
            "teerthaPrasada": 0
        },
        "address": "dwA",
        "bookedBy": "",
        "devoteeName": "Raj",
        "gothra": "Vishnu Mardhana",
        "mobilenumber": "9911223344",
        "momento": "Category-1",
        "nakshtra": "Swati",
        "receiptDate": "24-08-2022",
        "receiptNo": "6493",
        "reference": ""
    },
    "6494": {
        "M Navami Sampoorna Annadana Seva": {
            "Number": 0,
            "additionalCost": 0,
            "count": 1,
            "sevaCost": 10000,
            "sevaId": 23,
            "sevaName": "M Navami Sampoorna Annadana Seva",
            "sevaTime": "08:00 AM",
            "sevaType": 3,
            "teerthaPrasada": 0
        },
        "address": "fds",
        "bookedBy": "",
        "devoteeName": "Raj",
        "gothra": "Vishnu Mardhana",
        "mobilenumber": "9911223344",
        "momento": "Category-1",
        "nakshtra": "Swati",
        "receiptDate": "24-08-2022",
        "receiptNo": "6494",
        "reference": ""
    },
    "6495": {
        "Dwadashi Hasthodaka": {
            "Number": 0,
            "additionalCost": 0,
            "count": 1,
            "sevaCost": 50,
            "sevaId": 4,
            "sevaName": "Dwadashi Hasthodaka",
            "sevaTime": "08:00 AM",
            "sevaType": 1,
            "teerthaPrasada": 0
        },
        "Hasthodaka Regular": {
            "Number": 0,
            "additionalCost": 0,
            "count": 1,
            "sevaCost": 250,
            "sevaId": 108,
            "sevaName": "Hasthodaka Regular",
            "sevaTime": "08:00 AM",
            "sevaType": 1,
            "teerthaPrasada": 0
        },
        "M Navami Pavamana Homa": {
            "Number": 0,
            "additionalCost": 0,
            "count": 1,
            "sevaCost": 5000,
            "sevaId": 24,
            "sevaName": "M Navami Pavamana Homa",
            "sevaTime": "08:00 AM",
            "sevaType": 3,
            "teerthaPrasada": 10
        },
        "M Navami Sampoorna Annadana Seva": {
            "Number": 0,
            "additionalCost": 0,
            "count": 1,
            "sevaCost": 10000,
            "sevaId": 23,
            "sevaName": "M Navami Sampoorna Annadana Seva",
            "sevaTime": "08:00 AM",
            "sevaType": 3,
            "teerthaPrasada": 0
        },
        "PP - Rent": {
            "Number": 1702043745,
            "additionalCost": 0,
            "count": 1,
            "sevaCost": 7500,
            "sevaId": 20,
            "sevaName": "PP - Rent",
            "sevaTime": "08:00 AM",
            "sevaType": 14,
            "teerthaPrasada": 0
        },
        "Serva Seva": {
            "Number": 0,
            "additionalCost": 0,
            "count": 1,
            "sevaCost": 500,
            "sevaId": 37,
            "sevaName": "Serva Seva",
            "sevaTime": "08:00 AM",
            "sevaType": 1,
            "teerthaPrasada": 0
        },
        "address": "cdsa",
        "bookedBy": "",
        "devoteeName": "Raj",
        "gothra": "Vishnu Mardhana",
        "mobilenumber": "9911223344",
        "momento": "Category-1",
        "nakshtra": "Swati",
        "receiptDate": "24-08-2022",
        "receiptNo": "6495",
        "reference": ""
    },
    "6496": {
        "M Navami Sampoorna Annadana Seva": {
            "Number": 0,
            "additionalCost": 0,
            "count": 1,
            "sevaCost": 10000,
            "sevaId": 23,
            "sevaName": "M Navami Sampoorna Annadana Seva",
            "sevaTime": "08:00 AM",
            "sevaType": 3,
            "teerthaPrasada": 0
        },
        "address": "vd",
        "bookedBy": "",
        "devoteeName": "Raj",
        "gothra": "Vishnu Mardhana",
        "mobilenumber": "9911223344",
        "momento": "Category-1",
        "nakshtra": "Swati",
        "receiptDate": "24-08-2022",
        "receiptNo": "6496",
        "reference": ""
    },
    "6497": {
        "M Navami Sampoorna Annadana Seva": {
            "Number": 0,
            "additionalCost": 0,
            "count": 1,
            "sevaCost": 10000,
            "sevaId": 23,
            "sevaName": "M Navami Sampoorna Annadana Seva",
            "sevaTime": "08:00 AM",
            "sevaType": 3,
            "teerthaPrasada": 0
        },
        "address": "vfd",
        "bookedBy": "",
        "devoteeName": "Raj",
        "gothra": "Vishnu Mardhana",
        "hastodaka P P": {
            "Number": 0,
            "additionalCost": 0,
            "count": 1,
            "sevaCost": 200,
            "sevaId": 78,
            "sevaName": "hastodaka P P",
            "sevaTime": "08:00 AM",
            "sevaType": 5,
            "teerthaPrasada": 0
        },
        "mobilenumber": "9911223344",
        "momento": "Category-1",
        "nakshtra": "Swati",
        "receiptDate": "24-08-2022",
        "receiptNo": "6497",
        "reference": ""
    },
    "6498": {
        "M Navami Pavamana Homa": {
            "Number": 0,
            "additionalCost": 0,
            "count": 1,
            "sevaCost": 5000,
            "sevaId": 24,
            "sevaName": "M Navami Pavamana Homa",
            "sevaTime": "08:00 AM",
            "sevaType": 3,
            "teerthaPrasada": 0
        },
        "M Navami Sampoorna Annadana Seva": {
            "Number": 0,
            "additionalCost": 0,
            "count": 1,
            "sevaCost": 10000,
            "sevaId": 23,
            "sevaName": "M Navami Sampoorna Annadana Seva",
            "sevaTime": "08:00 AM",
            "sevaType": 3,
            "teerthaPrasada": 0
        },
        "address": "vfd",
        "bookedBy": "",
        "devoteeName": "Raj",
        "gothra": "Vishnu Mardhana",
        "mobilenumber": "9911223344",
        "momento": "Category-1",
        "nakshtra": "Swati",
        "receiptDate": "24-08-2022",
        "receiptNo": "6498",
        "reference": ""
    }
}
